<?xml version="1.0"?>
<FPONode xmlns:xsd="http://www.w3.org/2001/XMLSchema" xmlns:xsi="http://www.w3.org/2001/XMLSchema-instance">
  <flags>0</flags>
  <name>root</name>
  <pos>
    <x>0</x>
    <y>0</y>
    <z>0</z>
  </pos>
  <up>
    <x>0</x>
    <y>0</y>
    <z>0</z>
  </up>
  <dir>
    <x>0</x>
    <y>0</y>
    <z>0</z>
  </dir>
  <meshes />
  <children>
    <FPONode>
      <flags>0</flags>
      <name>STUB! id FF5F5C6C</name>
      <parentName>root</parentName>
      <pos>
        <x>-0.000841908448</x>
        <y>-0.0192784667</y>
        <z>-0.0305130482</z>
      </pos>
      <up>
        <x>4.294853E-08</x>
        <y>0.01745242</y>
        <z>0.9998477</z>
      </up>
      <dir>
        <x>4.370473E-08</x>
        <y>-0.9998477</y>
        <z>0.01745242</z>
      </dir>
      <meshes>
        <FPOmesh>
          <meshName>va_cc_Img0_Lod0</meshName>
          <lod>0</lod>
          <variant>0</variant>
        </FPOmesh>
        <FPOmesh>
          <meshName>va_cc_Img0_Lod1</meshName>
          <lod>1</lod>
          <variant>0</variant>
        </FPOmesh>
        <FPOmesh>
          <meshName>va_cc_Img0_Lod2</meshName>
          <lod>2</lod>
          <variant>0</variant>
        </FPOmesh>
        <FPOmesh>
          <meshName>va_cc_Img1_Lod0</meshName>
          <lod>0</lod>
          <variant>1</variant>
        </FPOmesh>
        <FPOmesh>
          <meshName>va_cc_Img1_Lod1</meshName>
          <lod>1</lod>
          <variant>1</variant>
        </FPOmesh>
        <FPOmesh>
          <meshName>va_cc_Img1_Lod2</meshName>
          <lod>2</lod>
          <variant>1</variant>
        </FPOmesh>
        <FPOmesh>
          <meshName>va_cc_Img2_Lod0</meshName>
          <lod>0</lod>
          <variant>2</variant>
        </FPOmesh>
        <FPOmesh>
          <meshName>va_cc_Img2_Lod1</meshName>
          <lod>1</lod>
          <variant>2</variant>
        </FPOmesh>
        <FPOmesh>
          <meshName>va_cc_Img2_Lod2</meshName>
          <lod>2</lod>
          <variant>2</variant>
        </FPOmesh>
      </meshes>
      <children>
        <FPONode>
          <flags>0</flags>
          <name>STUB! id 629595B3</name>
          <parentName>STUB! id FF5F5C6C</parentName>
          <pos>
            <x>-0.007822523</x>
            <y>3.34044576</y>
            <z>-1.8450036</z>
          </pos>
          <up>
            <x>2.23716683E-07</x>
            <y>-0.0174521822</y>
            <z>0.9998477</z>
          </up>
          <dir>
            <x>-2.9175888E-07</x>
            <y>0.9998477</y>
            <z>0.0174521822</z>
          </dir>
          <meshes>
            <FPOmesh>
              <meshName>va_cc_aerial_Img0_Lod0</meshName>
              <lod>0</lod>
              <variant>0</variant>
            </FPOmesh>
            <FPOmesh>
              <meshName>va_cc_aerial_Img0_Lod1</meshName>
              <lod>1</lod>
              <variant>0</variant>
            </FPOmesh>
            <FPOmesh>
              <meshName>va_cc_aerial_Img0_Lod2</meshName>
              <lod>2</lod>
              <variant>0</variant>
            </FPOmesh>
            <FPOmesh>
              <meshName>va_cc_aerial_Img1_Lod0</meshName>
              <lod>0</lod>
              <variant>1</variant>
            </FPOmesh>
            <FPOmesh>
              <meshName>va_cc_aerial_Img1_Lod1</meshName>
              <lod>1</lod>
              <variant>1</variant>
            </FPOmesh>
            <FPOmesh>
              <meshName>va_cc_aerial_Img1_Lod2</meshName>
              <lod>2</lod>
              <variant>1</variant>
            </FPOmesh>
            <FPOmesh>
              <meshName>va_cc_aerial_Img2_Lod0</meshName>
              <lod>0</lod>
              <variant>2</variant>
            </FPOmesh>
            <FPOmesh>
              <meshName>va_cc_aerial_Img2_Lod1</meshName>
              <lod>1</lod>
              <variant>2</variant>
            </FPOmesh>
            <FPOmesh>
              <meshName>va_cc_aerial_Img2_Lod2</meshName>
              <lod>2</lod>
              <variant>2</variant>
            </FPOmesh>
          </meshes>
          <children />
          <slots />
        </FPONode>
        <FPONode>
          <flags>0</flags>
          <name>STUB! id E73440A0</name>
          <parentName>STUB! id FF5F5C6C</parentName>
          <pos>
            <x>4.59768074E-07</x>
            <y>-0.3037586</y>
            <z>3.25242877</z>
          </pos>
          <up>
            <x>2.06802332E-15</x>
            <y>1</y>
            <z>1.877054E-15</z>
          </up>
          <dir>
            <x>-3.58102448E-15</x>
            <y>-1.877054E-15</y>
            <z>1</z>
          </dir>
          <meshes>
            <FPOmesh>
              <meshName>va_cc_glass_Img0_Lod0</meshName>
              <lod>0</lod>
              <variant>0</variant>
            </FPOmesh>
            <FPOmesh>
              <meshName>va_cc_glass_Img0_Lod1</meshName>
              <lod>1</lod>
              <variant>0</variant>
            </FPOmesh>
            <FPOmesh>
              <meshName>va_cc_glass_Img0_Lod2</meshName>
              <lod>2</lod>
              <variant>0</variant>
            </FPOmesh>
            <FPOmesh>
              <meshName>va_cc_glass_Img1_Lod0</meshName>
              <lod>0</lod>
              <variant>1</variant>
            </FPOmesh>
            <FPOmesh>
              <meshName>va_cc_glass_Img1_Lod1</meshName>
              <lod>1</lod>
              <variant>1</variant>
            </FPOmesh>
            <FPOmesh>
              <meshName>va_cc_glass_Img1_Lod2</meshName>
              <lod>2</lod>
              <variant>1</variant>
            </FPOmesh>
            <FPOmesh>
              <lod>0</lod>
              <variant>2</variant>
            </FPOmesh>
            <FPOmesh>
              <lod>1</lod>
              <variant>2</variant>
            </FPOmesh>
            <FPOmesh>
              <meshName>va_cc_glass_Img2_Lod2</meshName>
              <lod>2</lod>
              <variant>2</variant>
            </FPOmesh>
          </meshes>
          <children />
          <slots />
        </FPONode>
        <FPONode>
          <flags>0</flags>
          <name>STUB! id B351DFF6</name>
          <parentName>STUB! id FF5F5C6C</parentName>
          <pos>
            <x>3.808383</x>
            <y>-0.58823055</y>
            <z>-3.76489353</z>
          </pos>
          <up>
            <x>0.261706978</x>
            <y>0.9651473</y>
            <z>-0.000343152</z>
          </up>
          <dir>
            <x>-0.1631887</x>
            <y>0.0446002632</y>
            <z>0.9855862</z>
          </dir>
          <meshes>
            <FPOmesh>
              <meshName>va_cc_RightWingA_Img0_Lod0</meshName>
              <lod>0</lod>
              <variant>0</variant>
            </FPOmesh>
            <FPOmesh>
              <meshName>va_cc_RightWingA_Img0_Lod1</meshName>
              <lod>1</lod>
              <variant>0</variant>
            </FPOmesh>
            <FPOmesh>
              <meshName>va_cc_RightWingA_Img0_Lod2</meshName>
              <lod>2</lod>
              <variant>0</variant>
            </FPOmesh>
            <FPOmesh>
              <meshName>va_cc_RightWingA_Img1_Lod0</meshName>
              <lod>0</lod>
              <variant>1</variant>
            </FPOmesh>
            <FPOmesh>
              <meshName>va_cc_RightWingA_Img1_Lod1</meshName>
              <lod>1</lod>
              <variant>1</variant>
            </FPOmesh>
            <FPOmesh>
              <meshName>va_cc_RightWingA_Img1_Lod2</meshName>
              <lod>2</lod>
              <variant>1</variant>
            </FPOmesh>
            <FPOmesh>
              <meshName>va_cc_RightWingA_Img2_Lod0</meshName>
              <lod>0</lod>
              <variant>2</variant>
            </FPOmesh>
            <FPOmesh>
              <meshName>va_cc_RightWingA_Img2_Lod1</meshName>
              <lod>1</lod>
              <variant>2</variant>
            </FPOmesh>
            <FPOmesh>
              <meshName>va_cc_RightWingA_Img2_Lod2</meshName>
              <lod>2</lod>
              <variant>2</variant>
            </FPOmesh>
          </meshes>
          <children />
          <slots />
        </FPONode>
        <FPONode>
          <flags>0</flags>
          <name>STUB! id 37A5D899</name>
          <parentName>STUB! id FF5F5C6C</parentName>
          <pos>
            <x>6.813512</x>
            <y>-0.09102636</y>
            <z>-1.10137248</z>
          </pos>
          <up>
            <x>0.00451701833</x>
            <y>0.9999896</y>
            <z>0.0005945982</z>
          </up>
          <dir>
            <x>-0.258779645</x>
            <y>0.000594574667</y>
            <z>0.9659362</z>
          </dir>
          <meshes>
            <FPOmesh>
              <meshName>va_cc_RightWing_Img0_Lod0</meshName>
              <lod>0</lod>
              <variant>0</variant>
            </FPOmesh>
            <FPOmesh>
              <meshName>va_cc_RightWing_Img0_Lod1</meshName>
              <lod>1</lod>
              <variant>0</variant>
            </FPOmesh>
            <FPOmesh>
              <meshName>va_cc_RightWing_Img0_Lod2</meshName>
              <lod>2</lod>
              <variant>0</variant>
            </FPOmesh>
            <FPOmesh>
              <meshName>va_cc_RightWing_Img1_Lod0</meshName>
              <lod>0</lod>
              <variant>1</variant>
            </FPOmesh>
            <FPOmesh>
              <meshName>va_cc_RightWing_Img1_Lod1</meshName>
              <lod>1</lod>
              <variant>1</variant>
            </FPOmesh>
            <FPOmesh>
              <meshName>va_cc_RightWing_Img1_Lod2</meshName>
              <lod>2</lod>
              <variant>1</variant>
            </FPOmesh>
            <FPOmesh>
              <meshName>va_cc_RightWing_Img2_Lod0</meshName>
              <lod>0</lod>
              <variant>2</variant>
            </FPOmesh>
            <FPOmesh>
              <meshName>va_cc_RightWing_Img2_Lod1</meshName>
              <lod>1</lod>
              <variant>2</variant>
            </FPOmesh>
            <FPOmesh>
              <meshName>va_cc_RightWing_Img2_Lod2</meshName>
              <lod>2</lod>
              <variant>2</variant>
            </FPOmesh>
          </meshes>
          <children />
          <slots />
        </FPONode>
        <FPONode>
          <flags>0</flags>
          <name>STUB! id 87B297A1</name>
          <parentName>STUB! id FF5F5C6C</parentName>
          <pos>
            <x>2.97327614</x>
            <y>0.246435151</y>
            <z>-0.48235634</z>
          </pos>
          <up>
            <x>2.06802332E-15</x>
            <y>1</y>
            <z>1.877054E-15</z>
          </up>
          <dir>
            <x>-3.58102448E-15</x>
            <y>-1.877054E-15</y>
            <z>1</z>
          </dir>
          <meshes>
            <FPOmesh>
              <meshName>va_cc_RightGun_Img0_Lod0</meshName>
              <lod>0</lod>
              <variant>0</variant>
            </FPOmesh>
            <FPOmesh>
              <meshName>va_cc_RightGun_Img0_Lod1</meshName>
              <lod>1</lod>
              <variant>0</variant>
            </FPOmesh>
            <FPOmesh>
              <meshName>va_cc_RightGun_Img0_Lod2</meshName>
              <lod>2</lod>
              <variant>0</variant>
            </FPOmesh>
            <FPOmesh>
              <meshName>va_cc_RightGun_Img1_Lod0</meshName>
              <lod>0</lod>
              <variant>1</variant>
            </FPOmesh>
            <FPOmesh>
              <meshName>va_cc_RightGun_Img1_Lod1</meshName>
              <lod>1</lod>
              <variant>1</variant>
            </FPOmesh>
            <FPOmesh>
              <meshName>va_cc_RightGun_Img1_Lod2</meshName>
              <lod>2</lod>
              <variant>1</variant>
            </FPOmesh>
            <FPOmesh>
              <meshName>va_cc_RightGun_Img2_Lod0</meshName>
              <lod>0</lod>
              <variant>2</variant>
            </FPOmesh>
            <FPOmesh>
              <meshName>va_cc_RightGun_Img2_Lod1</meshName>
              <lod>1</lod>
              <variant>2</variant>
            </FPOmesh>
            <FPOmesh>
              <meshName>va_cc_RightGun_Img2_Lod2</meshName>
              <lod>2</lod>
              <variant>2</variant>
            </FPOmesh>
          </meshes>
          <children />
          <slots />
        </FPONode>
        <FPONode>
          <flags>0</flags>
          <name>STUB! id 31493196</name>
          <parentName>STUB! id FF5F5C6C</parentName>
          <pos>
            <x>-2.97327638</x>
            <y>0.246434927</y>
            <z>-0.482356638</z>
          </pos>
          <up>
            <x>2.06802332E-15</x>
            <y>1</y>
            <z>1.877054E-15</z>
          </up>
          <dir>
            <x>-3.58102448E-15</x>
            <y>-1.877054E-15</y>
            <z>1</z>
          </dir>
          <meshes>
            <FPOmesh>
              <meshName>va_cc_LeftGun_Img0_Lod0</meshName>
              <lod>0</lod>
              <variant>0</variant>
            </FPOmesh>
            <FPOmesh>
              <meshName>va_cc_LeftGun_Img0_Lod1</meshName>
              <lod>1</lod>
              <variant>0</variant>
            </FPOmesh>
            <FPOmesh>
              <meshName>va_cc_LeftGun_Img0_Lod2</meshName>
              <lod>2</lod>
              <variant>0</variant>
            </FPOmesh>
            <FPOmesh>
              <meshName>va_cc_LeftGun_Img1_Lod0</meshName>
              <lod>0</lod>
              <variant>1</variant>
            </FPOmesh>
            <FPOmesh>
              <meshName>va_cc_LeftGun_Img1_Lod1</meshName>
              <lod>1</lod>
              <variant>1</variant>
            </FPOmesh>
            <FPOmesh>
              <meshName>va_cc_LeftGun_Img1_Lod2</meshName>
              <lod>2</lod>
              <variant>1</variant>
            </FPOmesh>
            <FPOmesh>
              <meshName>va_cc_LeftGun_Img2_Lod0</meshName>
              <lod>0</lod>
              <variant>2</variant>
            </FPOmesh>
            <FPOmesh>
              <meshName>va_cc_LeftGun_Img2_Lod1</meshName>
              <lod>1</lod>
              <variant>2</variant>
            </FPOmesh>
            <FPOmesh>
              <meshName>va_cc_LeftGun_Img2_Lod2</meshName>
              <lod>2</lod>
              <variant>2</variant>
            </FPOmesh>
          </meshes>
          <children />
          <slots />
        </FPONode>
        <FPONode>
          <flags>0</flags>
          <name>STUB! id 8FAE8630</name>
          <parentName>STUB! id FF5F5C6C</parentName>
          <pos>
            <x>-6.813512</x>
            <y>-0.09102692</y>
            <z>-1.101373</z>
          </pos>
          <up>
            <x>-0.004517021</x>
            <y>0.9999896</y>
            <z>0.0005945755</z>
          </up>
          <dir>
            <x>0.258779645</x>
            <y>0.0005945973</y>
            <z>0.9659362</z>
          </dir>
          <meshes>
            <FPOmesh>
              <meshName>va_cc_LeftWing_Img0_Lod0</meshName>
              <lod>0</lod>
              <variant>0</variant>
            </FPOmesh>
            <FPOmesh>
              <meshName>va_cc_LeftWing_Img0_Lod1</meshName>
              <lod>1</lod>
              <variant>0</variant>
            </FPOmesh>
            <FPOmesh>
              <meshName>va_cc_LeftWing_Img0_Lod2</meshName>
              <lod>2</lod>
              <variant>0</variant>
            </FPOmesh>
            <FPOmesh>
              <meshName>va_cc_LeftWing_Img1_Lod0</meshName>
              <lod>0</lod>
              <variant>1</variant>
            </FPOmesh>
            <FPOmesh>
              <meshName>va_cc_LeftWing_Img1_Lod1</meshName>
              <lod>1</lod>
              <variant>1</variant>
            </FPOmesh>
            <FPOmesh>
              <meshName>va_cc_LeftWing_Img1_Lod2</meshName>
              <lod>2</lod>
              <variant>1</variant>
            </FPOmesh>
            <FPOmesh>
              <meshName>va_cc_LeftWing_Img2_Lod0</meshName>
              <lod>0</lod>
              <variant>2</variant>
            </FPOmesh>
            <FPOmesh>
              <meshName>va_cc_LeftWing_Img2_Lod1</meshName>
              <lod>1</lod>
              <variant>2</variant>
            </FPOmesh>
            <FPOmesh>
              <meshName>va_cc_LeftWing_Img2_Lod2</meshName>
              <lod>2</lod>
              <variant>2</variant>
            </FPOmesh>
          </meshes>
          <children />
          <slots />
        </FPONode>
        <FPONode>
          <flags>0</flags>
          <name>STUB! id 1CE3CFE4</name>
          <parentName>STUB! id FF5F5C6C</parentName>
          <pos>
            <x>-3.808382</x>
            <y>-0.5882316</y>
            <z>-3.76489425</z>
          </pos>
          <up>
            <x>-0.174014628</x>
            <y>0.9842816</y>
            <z>0.030144494</z>
          </up>
          <dir>
            <x>0.17063719</x>
            <y>-9.169741E-06</y>
            <z>0.9853339</z>
          </dir>
          <meshes>
            <FPOmesh>
              <meshName>va_cc_LeftWingA_Img0_Lod0</meshName>
              <lod>0</lod>
              <variant>0</variant>
            </FPOmesh>
            <FPOmesh>
              <meshName>va_cc_LeftWingA_Img0_Lod1</meshName>
              <lod>1</lod>
              <variant>0</variant>
            </FPOmesh>
            <FPOmesh>
              <meshName>va_cc_LeftWingA_Img0_Lod2</meshName>
              <lod>2</lod>
              <variant>0</variant>
            </FPOmesh>
            <FPOmesh>
              <meshName>va_cc_LeftWingA_Img1_Lod0</meshName>
              <lod>0</lod>
              <variant>1</variant>
            </FPOmesh>
            <FPOmesh>
              <meshName>va_cc_LeftWingA_Img1_Lod1</meshName>
              <lod>1</lod>
              <variant>1</variant>
            </FPOmesh>
            <FPOmesh>
              <meshName>va_cc_LeftWingA_Img1_Lod2</meshName>
              <lod>2</lod>
              <variant>1</variant>
            </FPOmesh>
            <FPOmesh>
              <meshName>va_cc_LeftWingA_Img2_Lod0</meshName>
              <lod>0</lod>
              <variant>2</variant>
            </FPOmesh>
            <FPOmesh>
              <meshName>va_cc_LeftWingA_Img2_Lod1</meshName>
              <lod>1</lod>
              <variant>2</variant>
            </FPOmesh>
            <FPOmesh>
              <meshName>va_cc_LeftWingA_Img2_Lod2</meshName>
              <lod>2</lod>
              <variant>2</variant>
            </FPOmesh>
          </meshes>
          <children />
          <slots />
        </FPONode>
      </children>
      <slots>
        <FPOSlot>
          <slotId>0</slotId>
          <name>1451338775</name>
          <pos>
            <x>1.1122632</x>
            <y>-1.19139874</y>
            <z>-2.08497357</z>
          </pos>
          <up>
            <x>3.05229065E-07</x>
            <y>0.0174523443</y>
            <z>-0.9998477</z>
          </up>
          <dir>
            <x>-1.83769984E-07</x>
            <y>-0.9998477</y>
            <z>-0.0174523443</z>
          </dir>
          <flags>0</flags>
        </FPOSlot>
        <FPOSlot>
          <slotId>1</slotId>
          <name>843915050</name>
          <pos>
            <x>0.8561437</x>
            <y>-0.329955131</y>
            <z>-4.65949345</z>
          </pos>
          <up>
            <x>5.61268862E-08</x>
            <y>-0.9998477</y>
            <z>-0.0174526069</z>
          </up>
          <dir>
            <x>1.32995126E-08</x>
            <y>0.0174526069</y>
            <z>-0.9998477</z>
          </dir>
          <flags>0</flags>
        </FPOSlot>
        <FPOSlot>
          <slotId>2</slotId>
          <name>1335911036</name>
          <pos>
            <x>1.98707139</x>
            <y>-0.814838767</y>
            <z>0.7783215</z>
          </pos>
          <up>
            <x>-3.13267577E-07</x>
            <y>0.9998477</y>
            <z>0.0174523778</z>
          </up>
          <dir>
            <x>-9.11981E-08</x>
            <y>-0.0174523778</y>
            <z>0.9998477</z>
          </dir>
          <flags>0</flags>
        </FPOSlot>
        <FPOSlot>
          <slotId>3</slotId>
          <name>1335911036</name>
          <pos>
            <x>-1.96286392</x>
            <y>-0.814838946</y>
            <z>0.7783213</z>
          </pos>
          <up>
            <x>-1.44825108E-07</x>
            <y>0.9998477</y>
            <z>0.0174527578</z>
          </up>
          <dir>
            <x>7.318264E-08</x>
            <y>-0.0174527578</y>
            <z>0.9998477</z>
          </dir>
          <flags>0</flags>
        </FPOSlot>
        <FPOSlot>
          <slotId>4</slotId>
          <name>1451338775</name>
          <pos>
            <x>-1.26575112</x>
            <y>-1.19139886</y>
            <z>-2.08497334</z>
          </pos>
          <up>
            <x>2.152407E-07</x>
            <y>0.0174523443</y>
            <z>-0.9998477</z>
          </up>
          <dir>
            <x>-1.66121467E-07</x>
            <y>-0.9998477</y>
            <z>-0.0174523443</z>
          </dir>
          <flags>1050930348</flags>
        </FPOSlot>
        <FPOSlot>
          <slotId>5</slotId>
          <name>843915050</name>
          <pos>
            <x>-1.01624191</x>
            <y>-0.32995522</y>
            <z>-4.659493</z>
          </pos>
          <up>
            <x>3.00549459E-07</x>
            <y>-0.9998477</y>
            <z>-0.017452227</z>
          </up>
          <dir>
            <x>5.01310673E-08</x>
            <y>0.017452227</y>
            <z>-0.9998477</z>
          </dir>
          <flags>1033145736</flags>
        </FPOSlot>
      </slots>
    </FPONode>
  </children>
  <slots />
</FPONode>